[
  {
    "fullName": "Justino Haselwood",
    "nationality": "HN",
    "dateOfBirth": "2021-06-19",
    "mostFamousMovie": "Goldengirl"
  },
  {
    "fullName": "Humbert Foad",
    "nationality": "RU",
    "dateOfBirth": "2021-10-14",
    "mostFamousMovie": "Good Son, The"
  },
  {
    "fullName": "Maureene Rominov",
    "nationality": "NI",
    "dateOfBirth": "2021-09-01",
    "mostFamousMovie": "Destiny (a.k.a. Between Two Worlds) (Der müde Tod)"
  },
  {
    "fullName": "Amalle Parlet",
    "nationality": "VE",
    "dateOfBirth": "2021-10-20",
    "mostFamousMovie": "Welcome to Sarajevo"
  },
  {
    "fullName": "Hallie Arnaldy",
    "nationality": "JP",
    "dateOfBirth": "2021-10-21",
    "mostFamousMovie": "Jesse Stone: No Remorse"
  },
  {
    "fullName": "Perkin Pendred",
    "nationality": "BR",
    "dateOfBirth": "2021-08-26",
    "mostFamousMovie": "Investigation of a Citizen Above Suspicion (Indagine su un cittadino al di sopra di ogni sospetto)"
  },
  {
    "fullName": "Bellanca Ahmed",
    "nationality": "CN",
    "dateOfBirth": "2021-10-09",
    "mostFamousMovie": "Caliber 9"
  },
  {
    "fullName": "Anica Pappi",
    "nationality": "ID",
    "dateOfBirth": "2021-12-13",
    "mostFamousMovie": "Madame Bovary"
  },
  {
    "fullName": "Vittoria Toop",
    "nationality": "ID",
    "dateOfBirth": "2021-10-11",
    "mostFamousMovie": "Firm, The"
  },
  {
    "fullName": "Devonne Heakey",
    "nationality": "PT",
    "dateOfBirth": "2022-04-12",
    "mostFamousMovie": "GhostWatcher"
  },
  {
    "fullName": "Elaina Vignaux",
    "nationality": "PH",
    "dateOfBirth": "2022-03-24",
    "mostFamousMovie": "Groove"
  },
  {
    "fullName": "Justine Rabidge",
    "nationality": "PH",
    "dateOfBirth": "2021-07-27",
    "mostFamousMovie": "Diamond Arm, The (Brilliantovaya ruka)"
  },
  {
    "fullName": "Jackson Zanni",
    "nationality": "GR",
    "dateOfBirth": "2021-07-06",
    "mostFamousMovie": "In the Basement"
  },
  {
    "fullName": "Dixie Jiru",
    "nationality": "PT",
    "dateOfBirth": "2022-01-25",
    "mostFamousMovie": "Running"
  },
  {
    "fullName": "Lark Vahl",
    "nationality": "CN",
    "dateOfBirth": "2021-08-10",
    "mostFamousMovie": "The Beaver Trilogy"
  },
  {
    "fullName": "Malinde Capoun",
    "nationality": "CZ",
    "dateOfBirth": "2021-11-03",
    "mostFamousMovie": "American Friends"
  },
  {
    "fullName": "Aluin Boig",
    "nationality": "SE",
    "dateOfBirth": "2021-09-10",
    "mostFamousMovie": "Country Girl, The"
  },
  {
    "fullName": "Roxanne Walkey",
    "nationality": "CN",
    "dateOfBirth": "2021-07-05",
    "mostFamousMovie": "Tape"
  },
  {
    "fullName": "Corissa Vannoni",
    "nationality": "CN",
    "dateOfBirth": "2021-10-23",
    "mostFamousMovie": "The Rise"
  },
  {
    "fullName": "Ogdan Shilvock",
    "nationality": "PH",
    "dateOfBirth": "2022-01-26",
    "mostFamousMovie": "Pretty Sweet"
  },
  {
    "fullName": "Ingrim Boik",
    "nationality": "UG",
    "dateOfBirth": "2022-01-24",
    "mostFamousMovie": "Battles Without Honor & Humanity (Jingi naki tatakai)"
  },
  {
    "fullName": "Faina Kasparski",
    "nationality": "CN",
    "dateOfBirth": "2021-12-24",
    "mostFamousMovie": "Baby Boy"
  },
  {
    "fullName": "Alison McGurgan",
    "nationality": "RU",
    "dateOfBirth": "2021-10-07",
    "mostFamousMovie": "Silent Night, Deadly Night 5: The Toy Maker"
  },
  {
    "fullName": "Norman Grioli",
    "nationality": "CN",
    "dateOfBirth": "2021-08-16",
    "mostFamousMovie": "Dog Nail Clipper (Koirankynnenleikkaaja)"
  },
  {
    "fullName": "Noell Kaspar",
    "nationality": "KZ",
    "dateOfBirth": "2022-02-14",
    "mostFamousMovie": "Home of the Brave"
  },
  {
    "fullName": "Jeremiah Faires",
    "nationality": "ID",
    "dateOfBirth": "2022-01-13",
    "mostFamousMovie": "The Casino Murder Case"
  },
  {
    "fullName": "Greg Brann",
    "nationality": "CN",
    "dateOfBirth": "2022-01-22",
    "mostFamousMovie": "Window to Paris (Okno v Parizh)"
  },
  {
    "fullName": "Baldwin Ratter",
    "nationality": "CN",
    "dateOfBirth": "2022-03-31",
    "mostFamousMovie": "Prodigal, The"
  },
  {
    "fullName": "Petunia Tarbath",
    "nationality": "CN",
    "dateOfBirth": "2021-12-18",
    "mostFamousMovie": "Fox, The"
  },
  {
    "fullName": "Lesley Bello",
    "nationality": "PE",
    "dateOfBirth": "2021-07-29",
    "mostFamousMovie": "Deux mondes, Les"
  },
  {
    "fullName": "Verina Giacaponi",
    "nationality": "CN",
    "dateOfBirth": "2021-10-15",
    "mostFamousMovie": "Silver Stallion (Silver Brumpy, The)"
  },
  {
    "fullName": "Milty Tuny",
    "nationality": "GT",
    "dateOfBirth": "2021-06-20",
    "mostFamousMovie": "Max Dugan Returns"
  },
  {
    "fullName": "Lilla Jodlkowski",
    "nationality": "HU",
    "dateOfBirth": "2021-10-12",
    "mostFamousMovie": "Lucky Numbers"
  },
  {
    "fullName": "Inna Tosney",
    "nationality": "CO",
    "dateOfBirth": "2022-01-02",
    "mostFamousMovie": "Mr. Smith Goes to Washington"
  },
  {
    "fullName": "Melli Rawstron",
    "nationality": "JP",
    "dateOfBirth": "2021-12-11",
    "mostFamousMovie": "Cruel Intentions"
  },
  {
    "fullName": "Cosetta Jephcote",
    "nationality": "RU",
    "dateOfBirth": "2021-08-12",
    "mostFamousMovie": "Chilly Scenes of Winter (Head Over Heels)"
  },
  {
    "fullName": "Bronson Spilsbury",
    "nationality": "CN",
    "dateOfBirth": "2022-03-02",
    "mostFamousMovie": "Koti-ikävä"
  },
  {
    "fullName": "Hoyt Neesham",
    "nationality": "CN",
    "dateOfBirth": "2021-09-23",
    "mostFamousMovie": "Water Horse: Legend of the Deep, The"
  },
  {
    "fullName": "Deni Rosenhaus",
    "nationality": "ID",
    "dateOfBirth": "2022-01-12",
    "mostFamousMovie": "Crime Spree"
  },
  {
    "fullName": "Kitti MacRedmond",
    "nationality": "ID",
    "dateOfBirth": "2021-12-25",
    "mostFamousMovie": "Battle: Los Angeles"
  },
  {
    "fullName": "Dorothea Tuddenham",
    "nationality": "SE",
    "dateOfBirth": "2022-05-14",
    "mostFamousMovie": "Intruders"
  },
  {
    "fullName": "Alfons Morcomb",
    "nationality": "SE",
    "dateOfBirth": "2022-05-08",
    "mostFamousMovie": "Bride Came C.O.D., The"
  },
  {
    "fullName": "Ardisj Dinsdale",
    "nationality": "SI",
    "dateOfBirth": "2021-11-01",
    "mostFamousMovie": "Moving Midway"
  },
  {
    "fullName": "Sigfried Guare",
    "nationality": "SE",
    "dateOfBirth": "2021-12-24",
    "mostFamousMovie": "The Four Feathers"
  },
  {
    "fullName": "Denice Giacomozzo",
    "nationality": "FR",
    "dateOfBirth": "2021-08-24",
    "mostFamousMovie": "Beastie Boys: Sabotage"
  },
  {
    "fullName": "Kelsey Lukash",
    "nationality": "ID",
    "dateOfBirth": "2022-02-21",
    "mostFamousMovie": "Topaze"
  },
  {
    "fullName": "Ami Pally",
    "nationality": "GR",
    "dateOfBirth": "2021-07-16",
    "mostFamousMovie": "Gospa"
  },
  {
    "fullName": "Onida Hylton",
    "nationality": "BI",
    "dateOfBirth": "2021-07-09",
    "mostFamousMovie": "Hitler: The Rise of Evil"
  },
  {
    "fullName": "Beaufort Saladin",
    "nationality": "IT",
    "dateOfBirth": "2021-11-13",
    "mostFamousMovie": "Invention of Lying, The"
  },
  {
    "fullName": "Pippo Ziemke",
    "nationality": "JP",
    "dateOfBirth": "2022-02-07",
    "mostFamousMovie": "Northwest Passage"
  },
  {
    "fullName": "Lee Glede",
    "nationality": "CN",
    "dateOfBirth": "2021-06-01",
    "mostFamousMovie": "Paper Will Be Blue, The (Hîrtia va fi albastrã)"
  },
  {
    "fullName": "Ruperta Matyukon",
    "nationality": "CO",
    "dateOfBirth": "2021-11-02",
    "mostFamousMovie": "Saving Silverman (Evil Woman)"
  },
  {
    "fullName": "Lilla Hilhouse",
    "nationality": "BR",
    "dateOfBirth": "2021-11-05",
    "mostFamousMovie": "Kid & I, The"
  },
  {
    "fullName": "Bernard Sherrum",
    "nationality": "CN",
    "dateOfBirth": "2022-04-14",
    "mostFamousMovie": "Intohimon vallassa"
  },
  {
    "fullName": "Beryl Fernie",
    "nationality": "CN",
    "dateOfBirth": "2022-04-05",
    "mostFamousMovie": "The Brain"
  },
  {
    "fullName": "Hastie Feldmark",
    "nationality": "NG",
    "dateOfBirth": "2022-05-11",
    "mostFamousMovie": "Poll Diaries, The (Poll)"
  },
  {
    "fullName": "Charissa Ateridge",
    "nationality": "BR",
    "dateOfBirth": "2022-04-29",
    "mostFamousMovie": "King Lear"
  },
  {
    "fullName": "Dew Blow",
    "nationality": "GR",
    "dateOfBirth": "2021-11-27",
    "mostFamousMovie": "Polar Express, The"
  },
  {
    "fullName": "Daron Mansell",
    "nationality": "ID",
    "dateOfBirth": "2021-08-23",
    "mostFamousMovie": "Killers, The"
  },
  {
    "fullName": "Guillaume Giacomo",
    "nationality": "FM",
    "dateOfBirth": "2021-11-14",
    "mostFamousMovie": "Court Jester, The"
  },
  {
    "fullName": "Stella Stean",
    "nationality": "CN",
    "dateOfBirth": "2022-01-22",
    "mostFamousMovie": "The Cheat"
  },
  {
    "fullName": "Alyss Hallihane",
    "nationality": "UZ",
    "dateOfBirth": "2021-12-20",
    "mostFamousMovie": "Sympathy for the Devil"
  },
  {
    "fullName": "Daloris Soares",
    "nationality": "BR",
    "dateOfBirth": "2021-12-04",
    "mostFamousMovie": "Any Number Can Win (Mélodie en sous-sol )"
  },
  {
    "fullName": "Gavin Brome",
    "nationality": "OM",
    "dateOfBirth": "2021-10-19",
    "mostFamousMovie": "Training Day"
  },
  {
    "fullName": "Kennett Buten",
    "nationality": "RU",
    "dateOfBirth": "2022-02-16",
    "mostFamousMovie": "Against The Sun"
  },
  {
    "fullName": "Miller Gotch",
    "nationality": "BR",
    "dateOfBirth": "2022-02-06",
    "mostFamousMovie": "Recess: School's Out"
  },
  {
    "fullName": "Joann Englishby",
    "nationality": "FR",
    "dateOfBirth": "2022-05-17",
    "mostFamousMovie": "Cry Freedom"
  },
  {
    "fullName": "Ermentrude Dedney",
    "nationality": "CN",
    "dateOfBirth": "2022-02-10",
    "mostFamousMovie": "Under the Flag of the Rising Sun"
  },
  {
    "fullName": "Krystalle Dodamead",
    "nationality": "ID",
    "dateOfBirth": "2021-08-06",
    "mostFamousMovie": "Sixth of the World, A (Shestaya chast mira)"
  },
  {
    "fullName": "Montgomery Breheny",
    "nationality": "CO",
    "dateOfBirth": "2022-04-17",
    "mostFamousMovie": "Shaggy Dog, The"
  },
  {
    "fullName": "Cesya Alen",
    "nationality": "BR",
    "dateOfBirth": "2021-08-04",
    "mostFamousMovie": "Contracted"
  },
  {
    "fullName": "Stacee Grelik",
    "nationality": "CN",
    "dateOfBirth": "2021-12-05",
    "mostFamousMovie": "Salvation Boulevard"
  },
  {
    "fullName": "Alley Doel",
    "nationality": "CN",
    "dateOfBirth": "2021-06-14",
    "mostFamousMovie": "Valentino: The Last Emperor"
  },
  {
    "fullName": "Randee Rowden",
    "nationality": "CN",
    "dateOfBirth": "2022-03-16",
    "mostFamousMovie": "Task, The"
  },
  {
    "fullName": "Marlo Treleven",
    "nationality": "PH",
    "dateOfBirth": "2021-08-21",
    "mostFamousMovie": "Yes, But... (Oui, mais...)"
  },
  {
    "fullName": "Margery Orpwood",
    "nationality": "CN",
    "dateOfBirth": "2021-11-17",
    "mostFamousMovie": "Wings (Krylya)"
  },
  {
    "fullName": "Shalom Dorricott",
    "nationality": "PL",
    "dateOfBirth": "2022-03-09",
    "mostFamousMovie": "Bride of the Wind"
  },
  {
    "fullName": "Sheridan Speight",
    "nationality": "US",
    "dateOfBirth": "2021-08-17",
    "mostFamousMovie": "Road North (Tie pohjoiseen)"
  },
  {
    "fullName": "Theodosia Timblett",
    "nationality": "ID",
    "dateOfBirth": "2022-05-16",
    "mostFamousMovie": "Children of Noisy Village, The (a.k.a Children of Bullerby Village, The) (Alla vi barn i Bullerbyn)"
  },
  {
    "fullName": "Elly Strotone",
    "nationality": "HR",
    "dateOfBirth": "2021-10-03",
    "mostFamousMovie": "The Walking Hills"
  },
  {
    "fullName": "Fancie Molloy",
    "nationality": "US",
    "dateOfBirth": "2021-09-20",
    "mostFamousMovie": "Tuesdays with Morrie"
  },
  {
    "fullName": "Fanya Chicotti",
    "nationality": "ID",
    "dateOfBirth": "2021-10-01",
    "mostFamousMovie": "Eccentricities of a Blonde-haired Girl (Singularidades de uma Rapariga Loura)"
  },
  {
    "fullName": "Che Peacher",
    "nationality": "CN",
    "dateOfBirth": "2021-07-20",
    "mostFamousMovie": "On the Riviera"
  },
  {
    "fullName": "Carlos Barsam",
    "nationality": "CO",
    "dateOfBirth": "2021-10-28",
    "mostFamousMovie": "Wipers Times, The"
  },
  {
    "fullName": "Izak Senecaut",
    "nationality": "JP",
    "dateOfBirth": "2022-04-18",
    "mostFamousMovie": "Ask Me Anything"
  },
  {
    "fullName": "Shay Embery",
    "nationality": "CN",
    "dateOfBirth": "2021-06-28",
    "mostFamousMovie": "Seoul Searching"
  },
  {
    "fullName": "Merwin Grandham",
    "nationality": "ID",
    "dateOfBirth": "2022-04-03",
    "mostFamousMovie": "Common"
  },
  {
    "fullName": "Roderigo Denisovo",
    "nationality": "GE",
    "dateOfBirth": "2021-05-31",
    "mostFamousMovie": "Deadfall"
  },
  {
    "fullName": "Giraud Bowen",
    "nationality": "TH",
    "dateOfBirth": "2021-07-16",
    "mostFamousMovie": "Muck"
  },
  {
    "fullName": "Barny Conroy",
    "nationality": "ID",
    "dateOfBirth": "2021-10-19",
    "mostFamousMovie": "Calling Dr. Death"
  },
  {
    "fullName": "Betsy Tittletross",
    "nationality": "FR",
    "dateOfBirth": "2021-11-18",
    "mostFamousMovie": "Message in a Bottle"
  },
  {
    "fullName": "Mariya Pantecost",
    "nationality": "UA",
    "dateOfBirth": "2022-02-28",
    "mostFamousMovie": "Secuestro Express"
  },
  {
    "fullName": "Ethan Westmarland",
    "nationality": "AM",
    "dateOfBirth": "2021-12-11",
    "mostFamousMovie": "Once Upon a Time in America"
  },
  {
    "fullName": "Debi Osmon",
    "nationality": "AR",
    "dateOfBirth": "2021-10-14",
    "mostFamousMovie": "Demon Lover Diary"
  },
  {
    "fullName": "Loutitia Cuseick",
    "nationality": "CN",
    "dateOfBirth": "2021-08-03",
    "mostFamousMovie": "The Vixen"
  },
  {
    "fullName": "Constancy Kelshaw",
    "nationality": "ET",
    "dateOfBirth": "2022-03-28",
    "mostFamousMovie": "Trials of Muhammad Ali, The"
  },
  {
    "fullName": "Ekaterina Curee",
    "nationality": "PL",
    "dateOfBirth": "2022-05-07",
    "mostFamousMovie": "Buddies (Colegas)"
  },
  {
    "fullName": "Wells Melburg",
    "nationality": "CN",
    "dateOfBirth": "2021-09-05",
    "mostFamousMovie": "Summer Place, A"
  },
  {
    "fullName": "Hansiain Sacco",
    "nationality": "CN",
    "dateOfBirth": "2021-09-18",
    "mostFamousMovie": "French Minister, The (Quai d'Orsay)"
  },
  {
    "fullName": "Cozmo Vila",
    "nationality": "ID",
    "dateOfBirth": "2021-09-13",
    "mostFamousMovie": "Hangar 18"
  }
]
